{"mc":{
	"effect_button":{
		"frameRate":12,
		"labels":[
			{"name":"effect","frame":1,"end":12}
			
			],
		"events":[
			
			],
		"frames":[
			
			{
			"res":"1",
			"x":-54,
			"y":-24
			},
			{
			"res":"2",
			"x":-53,
			"y":-24
			},
			{
			"res":"3",
			"x":-50,
			"y":-26
			},
			{
			"res":"4",
			"x":-38,
			"y":-26
			},
			{
			"res":"5",
			"x":-44,
			"y":-26
			},
			{
			"res":"6",
			"x":-52,
			"y":-27
			},
			{
			"res":"7",
			"x":-53,
			"y":-27
			},
			{
			"res":"8",
			"x":-54,
			"y":-27
			},
			{
			"res":"9",
			"x":-54,
			"y":-27
			},
			{
			"res":"10",
			"x":-55,
			"y":-26
			},
			{
			"res":"11",
			"x":-54,
			"y":-26
			},
			{
			"res":"12",
			"x":-54,
			"y":-25
			}
			]
}},
	"res":{
		"1":{"x":0,"y":111,"w":107,"h":52},
		"2":{"x":108,"y":0,"w":106,"h":52},
		"3":{"x":0,"y":55,"w":104,"h":54},
		"4":{"x":0,"y":165,"w":93,"h":53},
		"5":{"x":109,"y":110,"w":99,"h":53},
		"6":{"x":0,"y":0,"w":106,"h":53},
		"7":{"x":216,"y":0,"w":106,"h":51},
		"8":{"x":213,"y":54,"w":106,"h":52},
		"9":{"x":216,"y":108,"w":103,"h":53},
		"10":{"x":310,"y":163,"w":95,"h":53},
		"11":{"x":210,"y":163,"w":98,"h":53},
		"12":{"x":106,"y":55,"w":105,"h":53}
	}}