{"mc":{
	"effect_fly":{
		"frameRate":12,
		"labels":[
			{"name":"effect","frame":1,"end":12}
			
			],
		"events":[
			
			],
		"frames":[
			
			{
			"res":"01",
			"x":-127,
			"y":-329
			},
			{
			"res":"02",
			"x":-124,
			"y":-331
			},
			{
			"res":"03",
			"x":-123,
			"y":-328
			},
			{
			"res":"04",
			"x":-118,
			"y":-333
			},
			{
			"res":"05",
			"x":-120,
			"y":-333
			},
			{
			"res":"06",
			"x":-122,
			"y":-334
			},
			{
			"res":"07",
			"x":-122,
			"y":-333
			},
			{
			"res":"08",
			"x":-120,
			"y":-326
			},
			{
			"res":"09",
			"x":-122,
			"y":-325
			},
			{
			"res":"10",
			"x":-122,
			"y":-326
			},
			{
			"res":"11",
			"x":-122,
			"y":-322
			},
			{
			"res":"12",
			"x":-126,
			"y":-325
			}
			]
}},
	"res":{
		"10":{"x":509,"y":1,"w":255,"h":403},
		"11":{"x":512,"y":406,"w":251,"h":399},
		"12":{"x":254,"y":410,"w":256,"h":397},
		"02":{"x":254,"y":1,"w":253,"h":407},
		"01":{"x":766,"y":1,"w":256,"h":399},
		"09":{"x":244,"y":809,"w":243,"h":401},
		"06":{"x":1,"y":1,"w":251,"h":411},
		"08":{"x":512,"y":807,"w":244,"h":403},
		"04":{"x":1,"y":824,"w":238,"h":405},
		"03":{"x":758,"y":814,"w":244,"h":399},
		"05":{"x":1,"y":414,"w":241,"h":408},
		"07":{"x":766,"y":402,"w":249,"h":410}
	}}